django_grist_loader-0.3.0.dist-info/licenses/LICENSE
grist_loader/__init__.py
grist_loader/admin.py
grist_loader/apps.py
grist_loader/loader.py
grist_loader/models.py
grist_loader/management/commands/__init__.py
grist_loader/management/commands/grist_load_all.py
django_grist_loader-0.3.0.dist-info/METADATA
django_grist_loader-0.3.0.dist-info/WHEEL
django_grist_loader-0.3.0.dist-info/top_level.txt
django_grist_loader-0.3.0.dist-info/RECORD
