Metadata-Version: 2.4
Name: django-grist-loader
Version: 0.3.0
Summary: A reusable Django app to load data from Grist to Django models
Author-email: David Guillot <david.guillot@beta.gouv.fr>
Project-URL: Source, https://github.com/David-Guillot/django-grist-loader
Keywords: Django,Grist
Classifier: Development Status :: 4 - Beta
Classifier: Framework :: Django :: 4.2
Classifier: Framework :: Django :: 5.0
Classifier: Framework :: Django :: 5.1
Classifier: Framework :: Django :: 5.2
Classifier: Intended Audience :: Developers
Classifier: License :: OSI Approved :: MIT License
Classifier: Natural Language :: English
Classifier: Operating System :: OS Independent
Classifier: Programming Language :: Python :: 3 :: Only
Classifier: Programming Language :: Python :: 3.10
Classifier: Programming Language :: Python :: 3.11
Classifier: Programming Language :: Python :: 3.12
Classifier: Programming Language :: Python :: 3.13
Classifier: Programming Language :: Python :: Implementation :: CPython
Requires-Python: >=3.10
License-File: LICENSE
Requires-Dist: django<6,>=4.2
Requires-Dist: psycopg[binary]<4,>=3.2
Requires-Dist: pygrister~=0.6
Dynamic: license-file
